Workbook

Sheet CONTROL
A1: EL BOTÁNICO - PANEL DE CONTROL
D2: Indicador | E2: Valor
A3: Ventas Totales | B3: =SUM(Ventas!H:H) -> 8702400 | D3: Ventas Totales | E3: =B3 -> 8702400
A4: Costos Totales | B4: =SUM(Costos!D:D) -> 120984.34 | D4: Costos Totales | E4: =B4 -> 120984.34
A5: Ganancia Neta | B5: =B3-B4 -> 8581415.7 | D5: Ganancia Neta | E5: =B5 -> 8581415.7
A6: Valor de Stock | B6: =SUM(#REF!) -> #REF! | D6: Valor de Stock | E6: =B6 -> #REF!
A11: EGRESOS
A12: BALANZA | B12: 10900
A13: LIBRERÍA | B13: 18000
A14: BOLSAS DE ARPILLERA | B14: 20000
A15: MARTITA HIJO | B15: 571200
A16: POLISOL | B16: 25000
A17: PARAGUAYA | B17: 175000
A18: MARTITA HIJO | B18: 150000 | D18: *
A19: MARTITA HIJO | B19: 187000
A20: PARAGUAYA | B20: 193000
A21: LUIS ANDRADE | B21: 223800
A22: COMPRAS MACETS JUJEÑO | B22: 152000
A23: NORTE GRAFICA | B23: 25600
A24: MEDIA SOMBRA | B24: 112000
A25: FLETE POSTES | B25: 60000
A26: VENTILADOR | B26: 45000
A27: VENTI | B27: 30000
A28: MANTILLO | B28: 25000
A29: CLAUDIIO | B29: 80000
A30: VEGUITA | B30: 80000
... A45: BRASILERO | B45: 253000
A46: SECHEEP | B46: =11656+14101.46 -> 25757.46
A47: MAURO | B47: 15000
A48: PICA PICA | B48: 30000
A49: CLAUDIO | B49: 60000
A50: TIERRA NEGRA | B50: 170000
A51: BOMBA RIEGO | B51: 118000
A52: PIUNTURA | B52: 16000
A53: SAMEEP | B53: 39504.26
A54: ARENA | B54: 97000
A55: ELECTRICIDAD | B55: 81830
A56: cemento | B56: 32000
A57: GABRIEL MARTITA HIJO | B57: 300000
A58: transplantes raul luquitas | B58: 120000
... A77: PORTA | B77: 251240
B78: =SUM(B12:B77) -> 8138466.7
B81: =+Ventas!J2-B78 -> 700933.28
G88: K ,/85 | H88: 3´)

Sheet COMPRAS
A1: ESPECIE | B1: Maceta (LTS.) | C1: Cantidad | D1: Costo Unit.
A2: HERBACEAS PERENNES/CADUCAS
A3: AGAVE AMERICANO
A4: AGAVE AMERICANO VARIEGADO
A5: AGAVE ANGUSTIFOLIA MAGUEY
A6: AGAVE ATENUATA
A7: AGAVE DESMETTIANA
A8: AGAVE DESMETTIANA VARIEGADO
A9: AGLONEMA FREEDMAN | B9: 3 | C9: 3 | D9: 12828
A10: AGLONEMA PATTAYA | B10: 2/3L | C10: 10 | D10: 12828
A11: AGLONEMA PINK | B11: 3 | C11: 10 | D11: 4000
A12: ALEGRIA DEL HOGAR | C12: =14+45+15 -> 74 | D12: 700
A13: ALISO DE MAR (LOBULARIA MARITIMA) | B13: 1 | C13: =2+10+8+20+20 -> 60 | D13: 1500
A14: ALPINIA | B14: 3 | C14: 24 | D14: 3000
A15: ALTERNANTHERA BRASILIANA | F15: 6
A16: ALTERNANTHERA FICOIDEA RED
A17: ALTERNANTHERA FICOIDEA VERDE
A18: ALOCACIA (OREJA DE ELEFANTE) CHICA | C18: =4+5 -> 9 | D18: =14000/4 -> 3500
A19: ALOCACIA (OREJA DE ELEFANTE) MEDIANA | C19: 7 | D19: 5000
A20: ALOCACIA (OREJA DE ELEFANTE) GRANDE | B20: M15 | C20: 2 | D20: =32000/2 -> 16000
A21: ANTHURIUM | B21: 3/5L | C21: 14 | D21: 0
A22: ANTHURIUM ROJO | B22: 0.9 | C22: 6 | D22: 10000
A23: ASTA DE CIERVO | C23: 3 | D23: 0
A24: ASCLEPIA | C24: 9 | D24: =22500/9 -> 2500
A25: AZUCENA DE MEXICO | B25: 2/3L | C25: 22 | D25: 0
A26: BEGONIA ALA DE ANGEL | B26: 5 | C26: 4 | D26: 0
A27: BEGONIA DRAGON | B27: 3 | C27: 10 | D27: 3000
A28: BEGONIA HIRTELLA | B28: 3 | C28: 5 | D28: 0
A29: BEGONIA BOOMER | B29: COLGANTE | C29: 3 | D29: 4500
A30: BEGONIA RED | C30: 12 | D30: 700
A31: BEGONIA REY (PLATEADA) | B31: COLGANTE | C31: 2 | D31: 5500
A32: BROMELIA (LAGRIMA DE REINA) | B32: 3 | C32: 4 | D32: 0
A33: BROMELIA FOSFORITO | B33: 1/2L | C33: 4 | D33: 0
A34: CALA BLANCA | C34: =5+4 -> 9 | D34: 6500
A35: CALATHEA MACOYANA | B35: 1.5 | C35: 5 | D35: 10000
A36: CALATHEA MACOYANA CHICA | B36: 0.5 | C36: 5 | D36: 3100
A37: CALATHEA MIL RAYAS | B37: 3 | C37: 5 | D37: 9000
A38: CALATHEA ZEBRINA | B38: 5 | C38: 5 | D38: 18000
A39: CALISTEMO | C39: 5 | D39: 3000
A40: CLAVELINA | C40: 60 | D40: 770
A41: CRISANTEMO | C41: 12 | D41: 7000
A42: COPETITO | C42: 15 | D42: 700
A43: CORTADERIA SELLOANA | C43: 8 | D43: =28000/8 -> 3500
A44: COLOCACIA ESCULENTA | B44: 3 | C44: 50 | D44: 2500
A45: CUARESMERO 7L | B45: 7 | C45: =2+4 -> 6 | D45: 18000
A46: CUARESMERO 5L | B46: 5 | C46: 5 | D46: 12000
A47: DIANELA | C47: =4+7+20 -> 31 | D47: 3000
A48: DIEFFENBACHIA MARIANA | B48: 3 | C48: 5 | D48: 8100
A49: DIETE | B49: 5 | C49: 120 | D49: 2600
A50: DIMORFOTECA (MARGARITA DEL CABO) | C50: 10 | D50: 2000
A51: DRACENA RUBRA | B51: 3/10L | C51: 10 | D51: 0
A52: DRACENA TRICOLOR | C52: 2 | D52: 3500
A53: DRACENA FRAGANS/LEMON | B53: 0.7 | C53: 6 | D53: 6000
A54: DRACENA WARNECKI | B54: 0.7 | C54: =7+7 -> 14 | D54: 6200
A55: DRACENA KIWI | B55: 3 | C55: 5 | D55: 6500
A56: DRACENA BABY | B56: 3 | C56: 5 | D56: 6500
A57: ESCUDO PERSA | C57: 3 | D57: 2500
A58: ESPATIFILO | B58: 3/5L | C58: 23 | D58: 0
A59: ESPATIFILO SENSACIÒN | B59: 10 | C59: 1 | D59: 0
A60: FITONIA | B60: M18 | C60: 3 | D60: 2400
A61: FLOR DE CARTON (DORSTENIA ELATA) | B61: 3 | C61: 1 | D61: 0
A62: FLORALES | C62: =105+15 -> 120 | D62: 700
A63: GAURA | C63: =13+20+10+25+10+20 -> 98 | D63: 3000
A64: GIRASOL | C64: =8+10 -> 18 | D64: 2000
A65: HELECHO MONO | C65: 7 | D65: =15000/5 -> 3000
A66: HELECHO PIEDRA | C66: 6 | D66: =18000/6 -> 3000
A67: HELECHO ESPARRAGO | B67: 2 | C67: 8 | D67: 0
A68: HELICONIA CHICA | C68: 10 | D68: 4800
A69: HELICONIA GRANDE | C69: 4 | D69: 12000
A70: HIPOESTES | C70: 60 | D70: 770
A71: LAZO DE AMOR | B71: 3 | C71: 11 | D71: 0
A72: LILIUM | C72: 6 | D72: 5500
A73: LIRIO DEL AMAZONAS | B73: 3/5L | C73: 23 | D73: 0
A74: LIRIO MATIZADO | C74: 3 | D74: 4000
A75: LOBELIA | C75: 60 | D75: 700
A76: MARANTA | B76: 3/5L | C76: 19 | D76: 4000
A77: MARANTA ORACIÒN | B77: 0.5 | C77: =6+9 -> 15 | D77: 3100
A78: MARGARITA | C78: 7 | D78: 1500
A79: MELINI | C79: =8+10 -> 18 | D79: 2500
A80: MONEDA VARIEGADA | B80: COLGANTE | C80: 3 | D80: 3800
A81: MONSTERA | C81: =4+10+8 -> 22 | D81: =10500/3 -> 3500
A82: MONSTERA GRANDE | C82: 8 | D82: 8500
A83: PALMA DEL VIAJERO | C83: 2 | D83: 120000
A84: PENACHO | C84: 15 | D84: 700
A85: PENNICETUM | C85: =10+10+30 -> 50 | D85: =25000/10 -> 2500
A86: PENSAMIENTO | B86: 0.5 | C86: 28 | D86: 770
A87: PENTA | C87: 6 | D87: 2500
A88: PETUNIA | C88: 15 | D88: 700
A89: PETUNIA AMARILLA COLGANTE | B89: COLGANTE | C89: 3 | D89: 4800
A90: PHILODENDRO SANGUINEA | B90: 3 | C90: 5 | D90: 4800
A91: PHILODENDRO VERDE | B91: 3 | C91: =3+4 -> 7 | D91: 6500
A92: PHILODENDRO WHITE PRINCESS | B92: 3 | C92: 3 | D92: 14000
A93: PIEL DE LEOPARDO (DRIMIOPSIS MACULATA) | B93: 3 | C93: 1 | D93: 0
A94: PORTULACA | C94: 30 | D94: 700
A95: POTUS | B95: 0.5 | C95: 4 | D95: 0
A96: POTUS LEMON | B96: COLGANTE | C96: 6 | D96: =21000/6 -> 3500
A97: POTUS VARIEGADO BLANCO | B97: 0.5 | C97: 6 | D97: =12000/6 -> 2000
A98: POTUS VARIEGADO VERDE | B98: COLGANTE | C98: 7 | D98: 3500
A99: PORTULACA (VERDOLAGA) | C99: 60 | D99: 700
A100: RETAMA | C100: 5 | D100: 5000
...

Sheet INVENTARIO
A1: ESPECIE | B1: Maceta (LTS.) | C1: Cantidad | D1: Costo Unit. | E1: Precio Venta | F1: Margen Neto | G1: Existencias
A2: HERBACEAS PERENNES/CADUCAS
A3: AGAVE AMERICANO | B3: =+COMPRAS!B3:B108 -> 0 | C3: =+InventarioTbl3[[#This Row],[Cantidad]] -> 0 | D3: =+InventarioTbl3[[#This Row],[Costo Unit.]] -> 0 | F3: =+E3-InventarioTbl34[[#This Row],[Costo Unit.]] -> 0 | G3: =C3-SUMIF(Ventas!D:D,"AGAVE AMERICANO",Ventas!F:F) -> 0
A4: AGAVE AMERICANO VARIEGADO | B4: =+COMPRAS!B4:B115 -> 0 | C4: =+InventarioTbl3[[#This Row],[Cantidad]] -> 0 | D4: =+InventarioTbl3[[#This Row],[Costo Unit.]] -> 0 | F4: =+E4-InventarioTbl34[[#This Row],[Costo Unit.]] -> 0 | G4: =C4-SUMIF(Ventas!D:D,"AGAVE AMERICANO VARIEGADO",Ventas!F:F) -> 0
A5: AGAVE ANGUSTIFOLIA MAGUEY | B5: =+COMPRAS!B5:B116 -> 0 | C5: =+InventarioTbl3[[#This Row],[Cantidad]] -> 0 | D5: =+InventarioTbl3[[#This Row],[Costo Unit.]] -> 0 | F5: =+E5-InventarioTbl34[[#This Row],[Costo Unit.]] -> 0 | G5: =C5-SUMIF(Ventas!D:D,"AGAVE ANGUSTIFOLIA MAGUEY",Ventas!F:F) -> 0
A6: AGAVE ATENUATA | B6: =+COMPRAS!B6:B117 -> 0 | C6: =+InventarioTbl3[[#This Row],[Cantidad]] -> 0 | D6: =+InventarioTbl3[[#This Row],[Costo Unit.]] -> 0 | F6: =+E6-InventarioTbl34[[#This Row],[Costo Unit.]] -> 0 | G6: =C6-SUMIF(Ventas!D:D,"AGAVE ATENUATA",Ventas!F:F) -> 0
A7: AGAVE DESMETTIANA | B7: =+COMPRAS!B7:B118 -> 0 | C7: =+InventarioTbl3[[#This Row],[Cantidad]] -> 0 | D7: =+InventarioTbl3[[#This Row],[Costo Unit.]] -> 0 | F7: =+E7-InventarioTbl34[[#This Row],[Costo Unit.]] -> 0 | G7: =C7-SUMIF(Ventas!D:D,"AGAVE DESMETTIANA VARIEGADO",Ventas!F:F) -> 0
A8: AGAVE DESMETTIANA VARIEGADO | B8: =+COMPRAS!B8:B119 -> 0 | C8: =+InventarioTbl3[[#This Row],[Cantidad]] -> 0 | D8: =+InventarioTbl3[[#This Row],[Costo Unit.]] -> 0 | F8: =+E8-InventarioTbl34[[#This Row],[Costo Unit.]] -> 0 | G8: =C8-SUMIF(Ventas!D:D,"AGAVE DESMETTIANA VARIEGADO",Ventas!F:F) -> 0
A9: AGLONEMA FREEDMAN | B9: =+COMPRAS!B9:B120 -> 3 | C9: =+InventarioTbl3[[#This Row],[Cantidad]] -> 3 | D9: =+InventarioTbl3[[#This Row],[Costo Unit.]] -> 12828 | E9: 20000 | F9: =+E9-InventarioTbl34[[#This Row],[Costo Unit.]] -> 7172 | G9: =C9-SUMIF(Ventas!D:D,"AGLONEMA FREEDMAN",Ventas!F:F) -> 3
A10: AGLONEMA PATTAYA | B10: =+COMPRAS!B10:B121 -> 2/3L | C10: =+InventarioTbl3[[#This Row],[Cantidad]] -> 10 | D10: =+InventarioTbl3[[#This Row],[Costo Unit.]] -> 12828 | E10: 20000 | F10: =+E10-InventarioTbl34[[#This Row],[Costo Unit.]] -> 7172 | G10: =C10-SUMIF(Ventas!D:D,"AGLONEMA PATTAYA",Ventas!F:F) -> 10
A11: AGLONEMA PINK | B11: =+COMPRAS!B11:B122 -> 3 | C11: =+InventarioTbl3[[#This Row],[Cantidad]] -> 10 | D11: =+InventarioTbl3[[#This Row],[Costo Unit.]] -> 4000 | E11: 9000 | F11: =+E11-InventarioTbl34[[#This Row],[Costo Unit.]] -> 5000 | G11: =C11-SUMIF(Ventas!D:D,"AGLONEMA PINK",Ventas!F:F) -> 6
A12: =+InventarioTbl3[[#This Row],[ESPECIE]] -> ALEGRIA DEL HOGAR | C12: =+InventarioTbl3[[#This Row],[Cantidad]] -> 74 | D12: =+InventarioTbl3[[#This Row],[Costo Unit.]] -> 700 | E12: 3000 | F12: =+E12-InventarioTbl34[[#This Row],[Costo Unit.]] -> 2300 | G12: =C12-SUMIF(Ventas!D:D,"ALEGRIA",Ventas!F:F) -> 73
A13: ALISO DE MAR (LOBULARIA MARITIMA) | B13: =+COMPRAS!B13:B125 -> 1 | C13: =+InventarioTbl3[[#This Row],[Cantidad]] -> 60 | D13: =+InventarioTbl3[[#This Row],[Costo Unit.]] -> 1500 | E13: 3500 | F13: =+E13-InventarioTbl34[[#This Row],[Costo Unit.]] -> 2000 | G13: =C13-SUMIF(Ventas!D:D,"ALISO DE MAR",Ventas!F:F) -> 29
A14: ALPINIA | B14: =+COMPRAS!B14:B126 -> 3 | C14: =+InventarioTbl3[[#This Row],[Cantidad]] -> 24 | D14: =+InventarioTbl3[[#This Row],[Costo Unit.]] -> 3000 | E14: 12000 | F14: =+E14-InventarioTbl34[[#This Row],[Costo Unit.]] -> 9000 | G14: =C14-SUMIF(Ventas!D:D,"ALPINIA",Ventas!F:F) -> 23
A15: ALTERNANTHERA BRASILIANA | B15: =+COMPRAS!B15:B126 -> 0 | C15: =+InventarioTbl3[[#This Row],[Cantidad]] -> 0 | D15: =+InventarioTbl3[[#This Row],[Costo Unit.]] -> 0 | F15: =+E15-InventarioTbl34[[#This Row],[Costo Unit.]] -> 0 | G15: =C15-SUMIF(Ventas!D:D,"ALTERNANTHERA BRASILIANA",Ventas!F:F) -> 0
A16: ALTERNANTHERA FICOIDEA RED | B16: =+COMPRAS!B16:B127 -> 0 | C16: =+InventarioTbl3[[#This Row],[Cantidad]] -> 0 | D16: =+InventarioTbl3[[#This Row],[Costo Unit.]] -> 0 | F16: =+E16-InventarioTbl34[[#This Row],[Costo Unit.]] -> 0 | G16: =C16-SUMIF(Ventas!D:D,"ALTERNANTHERA FICOIDEA RED",Ventas!F:F) -> 0
A17: ALTERNANTHERA FICOIDEA VERDE | B17: =+COMPRAS!B17:B128 -> 0 | C17: =+InventarioTbl3[[#This Row],[Cantidad]] -> 0 | D17: =+InventarioTbl3[[#This Row],[Costo Unit.]] -> 0 | F17: =+E17-InventarioTbl34[[#This Row],[Costo Unit.]] -> 0 | G17: =C17-SUMIF(Ventas!D:D,"ALTERNANTHERA FICOIDEA VERDE",Ventas!F:F) -> 0
A18: =+InventarioTbl3[[#This Row],[ESPECIE]] -> ALOCACIA (OREJA DE ELEFANTE) CHICA | B18: =+COMPRAS!B18:B129 -> 0 | C18: =+InventarioTbl3[[#This Row],[Cantidad]] -> 9 | D18: =+InventarioTbl3[[#This Row],[Costo Unit.]] -> 3500 | E18: 10000 | F18: =+E18-InventarioTbl34[[#This Row],[Costo Unit.]] -> 6500 | G18: =C18-SUMIF(Ventas!D:D,"ALOCACIA CHICA",Ventas!F:F) -> 9
A19: =+InventarioTbl3[[#This Row],[ESPECIE]] -> ALOCACIA (OREJA DE ELEFANTE) MEDIANA | B19: =+COMPRAS!B19:B130 -> 0 | C19: =+InventarioTbl3[[#This Row],[Cantidad]] -> 7 | D19: =+InventarioTbl3[[#This Row],[Costo Unit.]] -> 5000 | E19: 15000 | F19: =+E19-InventarioTbl34[[#This Row],[Costo Unit.]] -> 10000 | G19: =C19-SUMIF(Ventas!D:D,"ALOCACIA MEDIANA",Ventas!F:F) -> 4
A20: =+InventarioTbl3[[#This Row],[ESPECIE]] -> ALOCACIA (OREJA DE ELEFANTE) GRANDE | B20: =+COMPRAS!B20:B130 -> M15 | C20: =+InventarioTbl3[[#This Row],[Cantidad]] -> 2 | D20: =+InventarioTbl3[[#This Row],[Costo Unit.]] -> 16000 | E20: 40000 | F20: =+E20-InventarioTbl34[[#This Row],[Costo Unit.]] -> 24000 | G20: =C20-SUMIF(Ventas!D:D,"ALOCACIA GRANDE",Ventas!F:F) -> 2
A21: ANTHURIUM | B21: =+COMPRAS!B21:B129 -> 3/5L | C21: =+InventarioTbl3[[#This Row],[Cantidad]] -> 14 | D21: =+InventarioTbl3[[#This Row],[Costo Unit.]] -> 0 | E21: 14000 | F21: =+E21-InventarioTbl34[[#This Row],[Costo Unit.]] -> 14000 | G21: =C21-SUMIF(Ventas!D:D,"ANTHURIUM",Ventas!F:F) -> 12
A22: ANTHURIUM ROJO | B22: =+COMPRAS!B22:B130 -> 0.9 | C22: =+InventarioTbl3[[#This Row],[Cantidad]] -> 6 | D22: =+InventarioTbl3[[#This Row],[Costo Unit.]] -> 10000 | E22: 13000 | F22: =+E22-InventarioTbl34[[#This Row],[Costo Unit.]] -> 3000 | G22: =C22-SUMIF(Ventas!D:D,"ANTHURIUM ROJO",Ventas!F:F) -> 6
A23: =+InventarioTbl3[[#This Row],[ESPECIE]] -> ASTA DE CIERVO | C23: =+InventarioTbl3[[#This Row],[Cantidad]] -> 3 | D23: =+InventarioTbl3[[#This Row],[Costo Unit.]] -> 0 | E23: 40000/60000 | G23: =C23-SUMIF(Ventas!D:D,"ASTA DE CIERVO",Ventas!F:F) -> 2
A24: =+COMPRAS!A24 -> ASCLEPIA | C24: =+InventarioTbl3[[#This Row],[Cantidad]] -> 9 | D24: =+InventarioTbl3[[#This Row],[Costo Unit.]] -> 2500 | E24: 7500 | F24: =+E24-InventarioTbl34[[#This Row],[Costo Unit.]] -> 5000 | G24: =C24-SUMIF(Ventas!D:D,"ASCLEPIA",Ventas!F:F) -> 6
A25: AZUCENA DE MEXICO | B25: =+COMPRAS!B25:B132 -> 2/3L | C25: =+InventarioTbl3[[#This Row],[Cantidad]] -> 22 | D25: =+InventarioTbl3[[#This Row],[Costo Unit.]] -> 0 | E25: 10000 | F25: =+E25-InventarioTbl34[[#This Row],[Costo Unit.]] -> 10000 | G25: =C25-SUMIF(Ventas!D:D,"AZUCENA DE MEXICO",Ventas!F:F) -> 21
A26: BEGONIA ALA DE ANGEL | B26: =+COMPRAS!B26:B133 -> 5 | C26: =+InventarioTbl3[[#This Row],[Cantidad]] -> 4 | D26: =+InventarioTbl3[[#This Row],[Costo Unit.]] -> 0 | E26: 10000 | F26: =+E26-InventarioTbl34[[#This Row],[Costo Unit.]] -> 10000 | G26: =C26-SUMIF(Ventas!D:D,"BEGONIA ALA DE ANGEL",Ventas!F:F) -> 4
A27: BEGONIA DRAGON | B27: =+COMPRAS!B27:B134 -> 3 | C27: =+InventarioTbl3[[#This Row],[Cantidad]] -> 10 | D27: =+InventarioTbl3[[#This Row],[Costo Unit.]] -> 3000 | E27: 10000 | F27: =+E27-InventarioTbl34[[#This Row],[Costo Unit.]] -> 7000 | G27: =C27-SUMIF(Ventas!D:D,"BEGONIA DRAGON",Ventas!F:F) -> 5
A28: BEGONIA HIRTELLA | B28: =+COMPRAS!B28:B135 -> 3 | C28: =+InventarioTbl3[[#This Row],[Cantidad]] -> 5 | D28: =+InventarioTbl3[[#This Row],[Costo Unit.]] -> 0 | E28: 10000 | F28: =+E28-InventarioTbl34[[#This Row],[Costo Unit.]] -> 10000 | G28: =C28-SUMIF(Ventas!D:D,"BEGONIA HIRTELLA",Ventas!F:F) -> 5
A29: BEGONIA BOOMER | B29: =+COMPRAS!B29:B136 -> COLGANTE | C29: =+InventarioTbl3[[#This Row],[Cantidad]] -> 3 | D29: =+InventarioTbl3[[#This Row],[Costo Unit.]] -> 4500 | E29: 10000 | F29: =+E29-InventarioTbl34[[#This Row],[Costo Unit.]] -> 5500 | G29: =C29-SUMIF(Ventas!D:D,"BEGONIA BOOMER",Ventas!F:F) -> 0
A30: =+InventarioTbl3[[#This Row],[ESPECIE]] -> BEGONIA RED | B30: =+COMPRAS!B30:B137 -> 0 | C30: =+InventarioTbl3[[#This Row],[Cantidad]] -> 12 | D30: =+InventarioTbl3[[#This Row],[Costo Unit.]] -> 700 | E30: 2500 | F30: =+E30-InventarioTbl34[[#This Row],[Costo Unit.]] -> 1800 | G30: =C30-SUMIF(Ventas!D:D,"BEGONIA RED",Ventas!F:F) -> 11
A31: =+InventarioTbl3[[#This Row],[ESPECIE]] -> BEGONIA REY (PLATEADA) | B31: =+COMPRAS!B31:B138 -> COLGANTE | C31: =+InventarioTbl3[[#This Row],[Cantidad]] -> 2 | D31: =+InventarioTbl3[[#This Row],[Costo Unit.]] -> 5500 | E31: 10000 | F31: =+E31-InventarioTbl34[[#This Row],[Costo Unit.]] -> 4500 | G31: =C31-SUMIF(Ventas!D:D,"BEGONIA REY",Ventas!F:F) -> 1
A32: BROMELIA (LAGRIMA DE REINA) | B32: =+COMPRAS!B32:B138 -> 3 | C32: =+InventarioTbl3[[#This Row],[Cantidad]] -> 4 | D32: =+InventarioTbl3[[#This Row],[Costo Unit.]] -> 0 | E32: 12000 | F32: =+E32-InventarioTbl34[[#This Row],[Costo Unit.]] -> 12000 | G32: =C32-SUMIF(Ventas!D:D,"BROMELIA",Ventas!F:F) -> 4
A33: BROMELIA FOSFORITO | B33: =+COMPRAS!B33:B140 -> 1/2L | C33: =+InventarioTbl3[[#This Row],[Cantidad]] -> 4 | D33: =+InventarioTbl3[[#This Row],[Costo Unit.]] -> 0 | E33: 15000 | F33: =+E33-InventarioTbl34[[#This Row],[Costo Unit.]] -> 15000 | G33: =C33-SUMIF(Ventas!D:D,"BROMELIA FOSFORITO",Ventas!F:F) -> 4
A34: =+InventarioTbl3[[#This Row],[ESPECIE]] -> CALA BLANCA | B34: =+COMPRAS!B34:B142 -> 0 | C34: =+InventarioTbl3[[#This Row],[Cantidad]] -> 9 | D34: =+InventarioTbl3[[#This Row],[Costo Unit.]] -> 6500 | E34: 12000 | F34: =+E34-InventarioTbl34[[#This Row],[Costo Unit.]] -> 5500 | G34: =C34-SUMIF(Ventas!D:D,"CALA BLANCA",Ventas!F:F) -> 5
A35: CALATHEA MACOYANA | B35: =+COMPRAS!B35:B142 -> 1.5 | C35: =+InventarioTbl3[[#This Row],[Cantidad]] -> 5 | D35: =+InventarioTbl3[[#This Row],[Costo Unit.]] -> 10000 | E35: 20000 | F35: =+E35-InventarioTbl34[[#This Row],[Costo Unit.]] -> 10000 | G35: =C35-SUMIF(Ventas!D:D,"CALATHEA MACOYANA",Ventas!F:F) -> 5
A36: =+InventarioTbl3[[#This Row],[ESPECIE]] -> CALATHEA MACOYANA CHICA | B36: =+COMPRAS!B36:B143 -> 0.5 | C36: =+InventarioTbl3[[#This Row],[Cantidad]] -> 5 | D36: =+InventarioTbl3[[#This Row],[Costo Unit.]] -> 3100 | E36: 10000 | F36: =+E36-InventarioTbl34[[#This Row],[Costo Unit.]] -> 6900 | G36: =C36-SUMIF(Ventas!D:D,"CALATHEA MACOYANA CHICA",Ventas!F:F) -> 3
A37: CALATHEA MIL RAYAS | B37: =+COMPRAS!B37:B143 -> 3 | C37: =+InventarioTbl3[[#This Row],[Cantidad]] -> 5 | D37: =+InventarioTbl3[[#This Row],[Costo Unit.]] -> 9000 | E37: 14000 | F37: =+E37-InventarioTbl34[[#This Row],[Costo Unit.]] -> 5000 | G37: =C37-SUMIF(Ventas!D:D,"CALATHEA MIL RAYAS",Ventas!F:F) -> 3
A38: CALATHEA ZEBRINA | B38: =+COMPRAS!B38:B144 -> 5 | C38: =+InventarioTbl3[[#This Row],[Cantidad]] -> 5 | D38: =+InventarioTbl3[[#This Row],[Costo Unit.]] -> 18000 | E38: 32000 | F38: =+E38-InventarioTbl34[[#This Row],[Costo Unit.]] -> 14000 | G38: =C38-SUMIF(Ventas!D:D,"CALATHEA ZEBRINA",Ventas!F:F) -> 0
A39: =+InventarioTbl3[[#This Row],[ESPECIE]] -> CALISTEMO | C39: =+InventarioTbl3[[#This Row],[Cantidad]] -> 5 | D39: =+InventarioTbl3[[#This Row],[Costo Unit.]] -> 3000 | E39: 10000 | F39: =+E39-InventarioTbl34[[#This Row],[Costo Unit.]] -> 7000 | G39: =C39-SUMIF(Ventas!D:D,"CALISTEMO",Ventas!F:F) -> 5
A40: =+InventarioTbl3[[#This Row],[ESPECIE]] -> CLAVELINA | C40: =+InventarioTbl3[[#This Row],[Cantidad]] -> 60 | D40: =+InventarioTbl3[[#This Row],[Costo Unit.]] -> 770 | E40: 3000 | F40: =+E40-InventarioTbl34[[#This Row],[Costo Unit.]] -> 2230 | G40: =C40-SUMIF(Ventas!D:D,"CLAVELINA",Ventas!F:F) -> 60
A41: =+InventarioTbl3[[#This Row],[ESPECIE]] -> CRISANTEMO | B41: =+COMPRAS!B41:B145 -> 0 | C41: =+InventarioTbl3[[#This Row],[Cantidad]] -> 12 | D41: =+InventarioTbl3[[#This Row],[Costo Unit.]] -> 7000 | E41: 12000 | F41: =+E41-InventarioTbl34[[#This Row],[Costo Unit.]] -> 5000 | G41: =C41-SUMIF(Ventas!D:D,"CRISANTEMO",Ventas!F:F) -> 0
A42: =+InventarioTbl3[[#This Row],[ESPECIE]] -> COPETITO | C42: =+InventarioTbl3[[#This Row],[Cantidad]] -> 15 | D42: =+InventarioTbl3[[#This Row],[Costo Unit.]] -> 700 | E42: 2500 | F42: =+E42-InventarioTbl34[[#This Row],[Costo Unit.]] -> 1800 | G42: =C42-SUMIF(Ventas!D:D,"COPETITO",Ventas!F:F) -> 11
A43: =+InventarioTbl3[#This Row] -> CORTADERIA SELLOANA | B43: =+COMPRAS!B43:B146 -> 0 | C43: =+InventarioTbl3[[#This Row],[Cantidad]] -> 8 | D43: =+InventarioTbl3[[#This Row],[Costo Unit.]] -> 3500 | E43: 9000 | F43: =+E43-InventarioTbl34[[#This Row],[Costo Unit.]] -> 5500 | G43: =C43-SUMIF(Ventas!D:D,"CORTADERIA",Ventas!F:F) -> 6
A44: COLOCACIA ESCULENTA | B44: =+COMPRAS!B44:B146 -> 3 | C44: =+InventarioTbl3[[#This Row],[Cantidad]] -> 50 | D44: =+InventarioTbl3[[#This Row],[Costo Unit.]] -> 2500 | E44: 15000 | F44: =+E44-InventarioTbl34[[#This Row],[Costo Unit.]] -> 12500 | G44: =C44-SUMIF(Ventas!D:D,"COLOCACIA ESCULENTA",Ventas!F:F) -> 35
A45: CUARESMERO 7L | B45: =+COMPRAS!B45:B147 -> 7 | C45: =+InventarioTbl3[[#This Row],[Cantidad]] -> 6 | D45: =+InventarioTbl3[[#This Row],[Costo Unit.]] -> 18000 | E45: 28000 | F45: =+E45-InventarioTbl34[[#This Row],[Costo Unit.]] -> 10000 | G45: =C45-SUMIF(Ventas!D:D,"CUARESMERO",Ventas!F:F) -> 5
A46: CUARESMERO 5L | B46: =+COMPRAS!B46:B148 -> 5 | C46: =+InventarioTbl3[[#This Row],[Cantidad]] -> 5 | D46: =+InventarioTbl3[[#This Row],[Costo Unit.]] -> 12000 | E46: 28000 | F46: =+E46-InventarioTbl34[[#This Row],[Costo Unit.]] -> 16000 | G46: =C46-SUMIF(Ventas!D:D,"CUARESMERO 5L",Ventas!F:F) -> 5
A47: =+InventarioTbl3[[#This Row],[ESPECIE]] -> DIANELA | B47: =+COMPRAS!B47:B149 -> 0 | C47: =+InventarioTbl3[[#This Row],[Cantidad]] -> 31 | D47: =+InventarioTbl3[[#This Row],[Costo Unit.]] -> 3000 | E47: 6000 | F47: =+E47-InventarioTbl34[[#This Row],[Costo Unit.]] -> 3000 | G47: =C47-SUMIF(Ventas!D:D,"DIANELA",Ventas!F:F) -> 24
A48: DIEFFENBACHIA MARIANA | B48: =+COMPRAS!B48:B149 -> 3 | C48: =+InventarioTbl3[[#This Row],[Cantidad]] -> 5 | D48: =+InventarioTbl3[[#This Row],[Costo Unit.]] -> 8100 | E48: 15000 | F48: =+E48-InventarioTbl34[[#This Row],[Costo Unit.]] -> 6900 | G48: =C48-SUMIF(Ventas!D:D,"DIEFFENBACHIA MARIANA",Ventas!F:F) -> 4
A49: DIETE | B49: =+COMPRAS!B49:B150 -> 5 | C49: =+InventarioTbl3[[#This Row],[Cantidad]] -> 120 | D49: =+InventarioTbl3[[#This Row],[Costo Unit.]] -> 2600 | E49: 6600 | F49: =+E49-InventarioTbl34[[#This Row],[Costo Unit.]] -> 4000 | G49: =C49-SUMIF(Ventas!D:D,"DIETE",Ventas!F:F) -> 65
A50: =+InventarioTbl3[[#This Row],[ESPECIE]] -> DIMORFOTECA (MARGARITA DEL CABO) | B50: =+COMPRAS!B50:B151 -> 0 | C50: =+InventarioTbl3[[#This Row],[Cantidad]] -> 10 | D50: =+InventarioTbl3[[#This Row],[Costo Unit.]] -> 2000 | E50: 2500 | F50: =+E50-InventarioTbl34[[#This Row],[Costo Unit.]] -> 500 | G50: =C50-SUMIF(Ventas!D:D,"DIMORFOTECA",Ventas!F:F) -> 5
A51: DRACENA RUBRA | B51: =+COMPRAS!B51:B151 -> 3/10L | C51: =+InventarioTbl3[[#This Row],[Cantidad]] -> 10 | D51: =+InventarioTbl3[[#This Row],[Costo Unit.]] -> 0 | E51: 20000 | F51: =+E51-InventarioTbl34[[#This Row],[Costo Unit.]] -> 20000 | G51: =C51-SUMIF(Ventas!D:D,"DRACENA RUBRA",Ventas!F:F) -> 9
A52: DRACENA TRICOLOR | B52: =+COMPRAS!B52:B152 -> 0 | C52: =+InventarioTbl3[[#This Row],[Cantidad]] -> 2 | D52: =+InventarioTbl3[[#This Row],[Costo Unit.]] -> 3500 | E52: 8500 | F52: =+E52-InventarioTbl34[[#This Row],[Costo Unit.]] -> 5000 | G52: =C52-SUMIF(Ventas!D:D,"DRACENA TRICOLOR",Ventas!F:F) -> 2
A53: DRACENA LEMON | B53: =+COMPRAS!B53:B153 -> 0.7 | C53: =+InventarioTbl3[[#This Row],[Cantidad]] -> 6 | D53: =+InventarioTbl3[[#This Row],[Costo Unit.]] -> 6000 | E53: 9000 | F53: =+E53-InventarioTbl34[[#This Row],[Costo Unit.]] -> 3000 | G53: =C53-SUMIF(Ventas!D:D,"DRACENA LEMON",Ventas!F:F) -> -1
A54: DRACENA WARNECKI | B54: =+COMPRAS!B54:B154 -> 0.7 | C54: =+InventarioTbl3[[#This Row],[Cantidad]] -> 14 | D54: =+InventarioTbl3[[#This Row],[Costo Unit.]] -> 6200 | E54: 12000 | F54: =+E54-InventarioTbl34[[#This Row],[Costo Unit.]] -> 5800 | G54: =C54-SUMIF(Ventas!D:D,"DRACENA WARNECKI",Ventas!F:F) -> 8
A55: =+InventarioTbl3[[#This Row],[ESPECIE]] -> DRACENA KIWI | B55: =+COMPRAS!B55:B155 -> 3 | C55: =+InventarioTbl3[[#This Row],[Cantidad]] -> 5 | D55: =+InventarioTbl3[[#This Row],[Costo Unit.]] -> 6500 | E55: 15000 | F55: =+E55-InventarioTbl34[[#This Row],[Costo Unit.]] -> 8500 | G55: =C55-SUMIF(Ventas!D:D,"DRACENA KIWI",Ventas!F:F) -> 4
A56: =+InventarioTbl3[[#This Row],[ESPECIE]] -> DRACENA BABY | B56: =+COMPRAS!B56:B156 -> 3 | C56: =+InventarioTbl3[[#This Row],[Cantidad]] -> 5 | D56: =+InventarioTbl3[[#This Row],[Costo Unit.]] -> 6500 | E56: 14000 | F56: =+E56-InventarioTbl34[[#This Row],[Costo Unit.]] -> 7500 | G56: =C56-SUMIF(Ventas!D:D,"DRACENA BABY",Ventas!F:F) -> 2
A57: =+InventarioTbl3[[#This Row],[ESPECIE]] -> ESCUDO PERSA | B57: =+COMPRAS!B57:B157 -> 0 | C57: =+InventarioTbl3[[#This Row],[Cantidad]] -> 3 | D57: =+InventarioTbl3[[#This Row],[Costo Unit.]] -> 2500 | E57: 3000 | F57: =+E57-InventarioTbl34[[#This Row],[Costo Unit.]] -> 500 | G57: =C57-SUMIF(Ventas!D:D,"ESCUDO PERSA",Ventas!F:F) -> 1
A58: ESPATIFILO | B58: =+COMPRAS!B58:B155 -> 3/5L | C58: =+InventarioTbl3[[#This Row],[Cantidad]] -> 23 | D58: =+InventarioTbl3[[#This Row],[Costo Unit.]] -> 0 | E58: 18000 | F58: =+E58-InventarioTbl34[[#This Row],[Costo Unit.]] -> 18000 | G58: =C58-SUMIF(Ventas!D:D,"ESPATIFILO",Ventas!F:F) -> 21
A59: ESPATIFILO SENSACIÒN | B59: =+COMPRAS!B59:B156 -> 10 | C59: =+InventarioTbl3[[#This Row],[Cantidad]] -> 1 | D59: =+InventarioTbl3[[#This Row],[Costo Unit.]] -> 0 | E59: 100000 | F59: =+E59-InventarioTbl34[[#This Row],[Costo Unit.]] -> 100000 | G59: =C59-SUMIF(Ventas!D:D,"ESPATIFILO SENSACION",Ventas!F:F) -> 1
A60: =+InventarioTbl3[[#This Row],[ESPECIE]] -> FITONIA | B60: =+COMPRAS!B60:B157 -> M18 | C60: =+InventarioTbl3[[#This Row],[Cantidad]] -> 3 | D60: =+InventarioTbl3[[#This Row],[Costo Unit.]] -> 2400 | E60: 4800 | F60: =+E60-InventarioTbl34[[#This Row],[Costo Unit.]] -> 2400 | G60: =C60-SUMIF(Ventas!D:D,"FITONIA",Ventas!F:F) -> 2
A61: FLOR DE CARTON (DORSTENIA ELATA) | B61: =+COMPRAS!B61:B157 -> 3 | C61: =+InventarioTbl3[[#This Row],[Cantidad]] -> 1 | D61: =+InventarioTbl3[[#This Row],[Costo Unit.]] -> 0 | E61: 20000 | F61: =+E61-InventarioTbl34[[#This Row],[Costo Unit.]] -> 20000 | G61: =C61-SUMIF(Ventas!D:D,"DORSTENIA",Ventas!F:F) -> 0
A62: =+InventarioTbl3[[#This Row],[ESPECIE]] -> FLORALES | B62: =+COMPRAS!B62:B158 -> 0 | C62: =+InventarioTbl3[[#This Row],[Cantidad]] -> 120 | D62: =+InventarioTbl3[[#This Row],[Costo Unit.]] -> 700 | E62: 1500 | F62: =+E62-InventarioTbl34[[#This Row],[Costo Unit.]] -> 800 | G62: =C62-SUMIF(Ventas!D:D,"FLORALES",Ventas!F:F) -> 28
A63: =+COMPRAS!A63 -> GAURA | B63: 3l | C63: =+InventarioTbl3[[#This Row],[Cantidad]] -> 98 | D63: =+InventarioTbl3[[#This Row],[Costo Unit.]] -> 3000 | E63: 8000 | F63: =+E63-InventarioTbl34[[#This Row],[Costo Unit.]] -> 5000 | G63: =C63-SUMIF(Ventas!D:D,"GAURA",Ventas!F:F) -> 31
A64: =+InventarioTbl3[[#This Row],[ESPECIE]] -> GIRASOL | B64: m18 | C64: =+InventarioTbl3[[#This Row],[Cantidad]] -> 18 | D64: =+InventarioTbl3[[#This Row],[Costo Unit.]] -> 2000 | E64: 4500 | F64: =+E64-InventarioTbl34[[#This Row],[Costo Unit.]] -> 2500 | G64: =C64-SUMIF(Ventas!D:D,"GIRASOL",Ventas!F:F) -> 10
A65: =+InventarioTbl3[[#This Row],[ESPECIE]] -> HELECHO MONO | B65: =+COMPRAS!B65:B159 -> 0 | C65: =+InventarioTbl3[[#This Row],[Cantidad]] -> 7 | D65: =+InventarioTbl3[[#This Row],[Costo Unit.]] -> 3000 | E65: 6500 | F65: =+E65-InventarioTbl34[[#This Row],[Costo Unit.]] -> 3500 | G65: =C65-SUMIF(Ventas!D:D,"HELECHO MONO",Ventas!F:F) -> 6
A66: =+InventarioTbl3[[#This Row],[ESPECIE]] -> HELECHO PIEDRA | B66: =+COMPRAS!B66:B167 -> 0 | C66: =+InventarioTbl3[[#This Row],[Cantidad]] -> 6 | D66: =+InventarioTbl3[[#This Row],[Costo Unit.]] -> 3000 | E66: 6500 | F66: =+E66-InventarioTbl34[[#This Row],[Costo Unit.]] -> 3500 | G66: =C66-SUMIF(Ventas!D:D,"HELECHO PIEDRA",Ventas!F:F) -> 2
A67: HELECHO ESPARRAGO | B67: =+COMPRAS!B67:B158 -> 2 | C67: =+InventarioTbl3[[#This Row],[Cantidad]] -> 8 | D67: =+InventarioTbl3[[#This Row],[Costo Unit.]] -> 0 | E67: 10000 | F67: =+E67-InventarioTbl34[[#This Row],[Costo Unit.]] -> 10000 | G67: =C67-SUMIF(Ventas!D:D,"HELECHO ESPARRAGO",Ventas!F:F) -> 7
A68: =+InventarioTbl3[[#This Row],[ESPECIE]] -> HELICONIA CHICA | B68: =+COMPRAS!B68:B159 -> 0 | C68: =+InventarioTbl3[[#This Row],[Cantidad]] -> 10 | D68: =+InventarioTbl3[[#This Row],[Costo Unit.]] -> 4800 | E68: 18000 | F68: =+E68-InventarioTbl34[[#This Row],[Costo Unit.]] -> 13200 | G68: =C68-SUMIF(Ventas!D:D,"HELICONIA CHICA",Ventas!F:F) -> 10
A69: =+InventarioTbl3[[#This Row],[ESPECIE]] -> HELICONIA GRANDE | B69: =+COMPRAS!B69:B160 -> 0 | C69: =+InventarioTbl3[[#This Row],[Cantidad]] -> 4 | D69: =+InventarioTbl3[[#This Row],[Costo Unit.]] -> 12000 | E69: 35000 | F69: =+E69-InventarioTbl34[[#This Row],[Costo Unit.]] -> 23000 | G69: =C69-SUMIF(Ventas!D:D,"HELICONIA GRANDE",Ventas!F:F) -> 4
A70: =+InventarioTbl3[[#This Row],[ESPECIE]] -> HIPOESTES | C70: =+InventarioTbl3[[#This Row],[Cantidad]] -> 60 | D70: =+InventarioTbl3[[#This Row],[Costo Unit.]] -> 770 | E70: 2500 | F70: =+E70-InventarioTbl34[[#This Row],[Costo Unit.]] -> 1730 | G70: =C70-SUMIF(Ventas!D:D,"HIPOESTES",Ventas!F:F) -> 48
A71: LAZO DE AMOR | B71: =+COMPRAS!B71:B158 -> 3 | C71: =+InventarioTbl3[[#This Row],[Cantidad]] -> 11 | D71: =+InventarioTbl3[[#This Row],[Costo Unit.]] -> 0 | E71: 7000 | F71: =+E71-InventarioTbl34[[#This Row],[Costo Unit.]] -> 7000 | G71: =C71-SUMIF(Ventas!D:D,"LAZO DE AMOR",Ventas!F:F) -> 7
A72: =+InventarioTbl3[[#This Row],[ESPECIE]] -> LILIUM | B72: =+COMPRAS!B72:B159 -> 0 | C72: =+InventarioTbl3[[#This Row],[Cantidad]] -> 6 | D72: =+InventarioTbl3[[#This Row],[Costo Unit.]] -> 5500 | E72: 10000 | F72: =+E72-InventarioTbl34[[#This Row],[Costo Unit.]] -> 4500 | G72: =C72-SUMIF(Ventas!D:D,"LILIUM",Ventas!F:F) -> 6
A73: LIRIO DEL AMAZONAS | B73: =+COMPRAS!B73:B159 -> 3/5L | C73: =+InventarioTbl3[[#This Row],[Cantidad]] -> 23 | D73: =+InventarioTbl3[[#This Row],[Costo Unit.]] -> 0 | E73: 8000 | F73: =+E73-InventarioTbl34[[#This Row],[Costo Unit.]] -> 8000 | G73: =C73-SUMIF(Ventas!D:D,"LIRIO DEL AMAZONAS",Ventas!F:F) -> 21
A74: =+InventarioTbl3[[#This Row],[ESPECIE]] -> LIRIO MATIZADO | B74: =+COMPRAS!B74:B160 -> 0 | C74: =+InventarioTbl3[[#This Row],[Cantidad]] -> 3 | D74: =+InventarioTbl3[[#This Row],[Costo Unit.]] -> 4000 | E74: 10000 | F74: =+E74-InventarioTbl34[[#This Row],[Costo Unit.]] -> 6000 | G74: =C74-SUMIF(Ventas!D:D,"LIRIO MATIZADO",Ventas!F:F) -> 3
A75: =+InventarioTbl3[[#This Row],[ESPECIE]] -> LOBELIA | B75: =+COMPRAS!B75:B160 -> 0 | C75: =+InventarioTbl3[[#This Row],[Cantidad]] -> 60 | D75: =+InventarioTbl3[[#This Row],[Costo Unit.]] -> 700 | E75: 3500 | F75: =+E75-InventarioTbl34[[#This Row],[Costo Unit.]] -> 2800 | G75: =C75-SUMIF(Ventas!D:D,"LOBELIA",Ventas!F:F) -> 58
A76: MARANTA | B76: =+COMPRAS!B76:B164 -> 3/5L | C76: =+InventarioTbl3[[#This Row],[Cantidad]] -> 19 | D76: =+InventarioTbl3[[#This Row],[Costo Unit.]] -> 4000 | E76: 15000 | F76: =+E76-InventarioTbl34[[#This Row],[Costo Unit.]] -> 11000 | G76: =C76-SUMIF(Ventas!D:D,"MARANTA",Ventas!F:F) -> 17
A77: MARANTA ORACIÒN | B77: =+COMPRAS!B77:B168 -> 0.5 | C77: =+InventarioTbl3[[#This Row],[Cantidad]] -> 15 | D77: =+InventarioTbl3[[#This Row],[Costo Unit.]] -> 3100 | E77: 6000 | F77: =+E77-InventarioTbl34[[#This Row],[Costo Unit.]] -> 2900 | G77: =C77-SUMIF(Ventas!D:D,"MARANTA ORACION",Ventas!F:F) -> 12
A78: MARGARITA | B78: =+COMPRAS!B78:B170 -> 0 | C78: =+InventarioTbl3[[#This Row],[Cantidad]] -> 7 | D78: =+InventarioTbl3[[#This Row],[Costo Unit.]] -> 1500 | E78: 3000 | F78: =+E78-InventarioTbl34[[#This Row],[Costo Unit.]] -> 1500 | G78: =C78-SUMIF(Ventas!D:D,"MARGARITA",Ventas!F:F) -> 4
A79: =+InventarioTbl3[[#This Row],[ESPECIE]] -> MELINI | C79: =+InventarioTbl3[[#This Row],[Cantidad]] -> 18 | D79: =+InventarioTbl3[[#This Row],[Costo Unit.]] -> 2500 | E79: 6500 | F79: =+E79-InventarioTbl34[[#This Row],[Costo Unit.]] -> 4000 | G79: =C79-SUMIF(Ventas!D:D,"MELINI",Ventas!F:F) -> 18
A80: =+InventarioTbl3[[#This Row],[ESPECIE]] -> MONEDA VARIEGADA | B80: COLGANTE | C80: =+InventarioTbl3[[#This Row],[Cantidad]] -> 3 | D80: =+InventarioTbl3[[#This Row],[Costo Unit.]] -> 3800 | E80: 10000 | F80: =+E80-InventarioTbl34[[#This Row],[Costo Unit.]] -> 6200 | G80: =C80-SUMIF(Ventas!D:D,"MONEDA VARIEGADA",Ventas!F:F) -> 1
A81: =+InventarioTbl3[[#This Row],[ESPECIE]] -> MONSTERA | B81: =+COMPRAS!B81:B171 -> 0 | C81: =+InventarioTbl3[[#This Row],[Cantidad]] -> 22 | D81: =+InventarioTbl3[[#This Row],[Costo Unit.]] -> 3500 | E81: 10000 | F81: =+E81-InventarioTbl34[[#This Row],[Costo Unit.]] -> 6500 | G81: =C81-SUMIF(Ventas!D:D,"MONSTERA",Ventas!F:F) -> 13
A82: =+InventarioTbl3[[#This Row],[ESPECIE]] -> MONSTERA GRANDE | B82: =+COMPRAS!B82:B172 -> 0 | C82: =+InventarioTbl3[[#This Row],[Cantidad]] -> 8 | D82: =+InventarioTbl3[[#This Row],[Costo Unit.]] -> 8500 | E82: 35000 | F82: =+E82-InventarioTbl34[[#This Row],[Costo Unit.]] -> 26500 | G82: =C82-SUMIF(Ventas!D:D,"MONSTERA GRANDE",Ventas!F:F) -> 8
A83: PALMA DEL VIAJERO | B83: =+COMPRAS!B83:B172 -> 0 | C83: =+InventarioTbl3[[#This Row],[Cantidad]] -> 2 | D83: =+InventarioTbl3[[#This Row],[Costo Unit.]] -> 120000 | E83: 240000 | F83: =+E83-InventarioTbl34[[#This Row],[Costo Unit.]] -> 120000 | G83: =C83-SUMIF(Ventas!D:D,"PALMA DEL VIAJERO",Ventas!F:F) -> 2
A84: =+COMPRAS!A84 -> PENACHO | B84: =+COMPRAS!B84:B173 -> 0 | C84: =+InventarioTbl3[[#This Row],[Cantidad]] -> 15 | D84: =+InventarioTbl3[[#This Row],[Costo Unit.]] -> 700 | E84: 2000 | F84: =+E84-InventarioTbl34[[#This Row],[Costo Unit.]] -> 1300 | G84: =C84-SUMIF(Ventas!D:D,"PENACHITO",Ventas!F:F) -> 15
A85: =+COMPRAS!A85 -> PENNICETUM | B85: =+COMPRAS!B85:B173 -> 0 | C85: =+InventarioTbl3[[#This Row],[Cantidad]] -> 50 | D85: =+InventarioTbl3[[#This Row],[Costo Unit.]] -> 2500 | E85: 5000 | F85: =+E85-InventarioTbl34[[#This Row],[Costo Unit.]] -> 2500 | G85: =C85-SUMIF(Ventas!D:D,"PENNICETUM",Ventas!F:F) -> 40
A86: PENSAMIENTO | B86: =+COMPRAS!B86:B172 -> 0.5 | C86: =+InventarioTbl3[[#This Row],[Cantidad]] -> 28 | D86: =+InventarioTbl3[[#This Row],[Costo Unit.]] -> 770 | E86: 2000 | F86: =+E86-InventarioTbl34[[#This Row],[Costo Unit.]] -> 1230 | G86: =C86-SUMIF(Ventas!D:D,"PENSAMIENTO",Ventas!F:F) -> 26
A87: PENTA | B87: =+COMPRAS!B87:B173 -> 0 | C87: =+InventarioTbl3[[#This Row],[Cantidad]] -> 6 | D87: =+InventarioTbl3[[#This Row],[Costo Unit.]] -> 2500 | E87: 5000 | F87: =+E87-InventarioTbl34[[#This Row],[Costo Unit.]] -> 2500 | G87: =C87-SUMIF(Ventas!D:D,"PENTA",Ventas!F:F) -> 2
A88: =+InventarioTbl3[[#This Row],[ESPECIE]] -> PETUNIA | B88: =+COMPRAS!B88:B174 -> 0 | C88: =+InventarioTbl3[[#This Row],[Cantidad]] -> 15 | D88: =+InventarioTbl3[[#This Row],[Costo Unit.]] -> 700 | E88: 2500 | F88: =+E88-InventarioTbl34[[#This Row],[Costo Unit.]] -> 1800 | G88: =C88-SUMIF(Ventas!D:D,"PETUNIA",Ventas!F:F) -> 13
A89: =+InventarioTbl3[[#This Row],[ESPECIE]] -> PETUNIA AMARILLA COLGANTE | B89: =+COMPRAS!B89:B173 -> COLGANTE | C89: =+InventarioTbl3[[#This Row],[Cantidad]] -> 3 | D89: =+InventarioTbl3[[#This Row],[Costo Unit.]] -> 4800 | E89: 9000 | F89: =+E89-InventarioTbl34[[#This Row],[Costo Unit.]] -> 4200 | G89: =C89-SUMIF(Ventas!D:D,"PETUNIA",Ventas!F:F) -> 1
A90: =+InventarioTbl3[[#This Row],[ESPECIE]] -> PHILODENDRO SANGUINEA | B90: =+COMPRAS!B90:B174 -> 3 | C90: =+InventarioTbl3[[#This Row],[Cantidad]] -> 5 | D90: =+InventarioTbl3[[#This Row],[Costo Unit.]] -> 4800 | E90: 20000 | F90: =+E90-InventarioTbl34[[#This Row],[Costo Unit.]] -> 15200 | G90: =C90-SUMIF(Ventas!D:D,"PHILODENDRO SANGUINEA",Ventas!F:F) -> 4
A91: =+InventarioTbl3[[#This Row],[ESPECIE]] -> PHILODENDRO VERDE | B91: =+COMPRAS!B91:B174 -> 3 | C91: =+InventarioTbl3[[#This Row],[Cantidad]] -> 7 | D91: =+InventarioTbl3[[#This Row],[Costo Unit.]] -> 6500 | E91: 15000 | F91: =+E91-InventarioTbl34[[#This Row],[Costo Unit.]] -> 8500 | G91: =C91-SUMIF(Ventas!D:D,"PHILODENDRO",Ventas!F:F) -> 6
A92: PHILODENDRO WHITE PRINCESS | B92: =+COMPRAS!B92:B170 -> 3 | C92: =+InventarioTbl3[[#This Row],[Cantidad]] -> 3 | D92: =+InventarioTbl3[[#This Row],[Costo Unit.]] -> 14000 | E92: 25000 | F92: =+E92-InventarioTbl34[[#This Row],[Costo Unit.]] -> 11000 | G92: =C92-SUMIF(Ventas!D:D,"PHILODENDRO WHITE PRINCESS",Ventas!F:F) -> 2
A93: PIEL DE LEOPARDO (DRIMIOPSIS MACULATA) | B93: =+COMPRAS!B93:B171 -> 3 | C93: =+InventarioTbl3[[#This Row],[Cantidad]] -> 1 | D93: =+InventarioTbl3[[#This Row],[Costo Unit.]] -> 0 | E93: 12000 | F93: =+E93-InventarioTbl34[[#This Row],[Costo Unit.]] -> 12000 | G93: =C93-SUMIF(Ventas!D:D,"PIEL DE LEOPARDO",Ventas!F:F) -> 1
A94: =+InventarioTbl3[[#This Row],[ESPECIE]] -> PORTULACA | C94: =+InventarioTbl3[[#This Row],[Cantidad]] -> 30 | D94: =+InventarioTbl3[[#This Row],[Costo Unit.]] -> 700 | E94: 3000 | F94: =+E94-InventarioTbl34[[#This Row],[Costo Unit.]] -> 2300 | G94: =C94-SUMIF(Ventas!D:D,"PORTULACA",Ventas!F:F) -> 30
A95: POTUS | B95: =+COMPRAS!B95:B173 -> 0.5 | C95: =+InventarioTbl3[[#This Row],[Cantidad]] -> 4 | D95: =+InventarioTbl3[[#This Row],[Costo Unit.]] -> 0 | E95: 4000 | F95: =+E95-InventarioTbl34[[#This Row],[Costo Unit.]] -> 4000 | G95: =C95-SUMIF(Ventas!D:D,"POTUS",Ventas!F:F) -> -3
A96: POTUS LEMON | B96: =+COMPRAS!B96:B174 -> COLGANTE | C96: =+InventarioTbl3[[#This Row],[Cantidad]] -> 6 | D96: =+InventarioTbl3[[#This Row],[Costo Unit.]] -> 3500 | E96: 8000 | F96: =+E96-InventarioTbl34[[#This Row],[Costo Unit.]] -> 4500 | G96: =C96-SUMIF(Ventas!D:D,"POTUS LEMON",Ventas!F:F) -> 5
A97: POTUS VARIEGADO BLANCO | B97: =+COMPRAS!B97:B175 -> 0.5 | C97: =+InventarioTbl3[[#This Row],[Cantidad]] -> 6 | D97: =+InventarioTbl3[[#This Row],[Costo Unit.]] -> 2000 | E97: 4000 | F97: =+E97-InventarioTbl34[[#This Row],[Costo Unit.]] -> 2000 | G97: =C97-SUMIF(Ventas!D:D,"POTUS VARIEGADO BLANCO",Ventas!F:F) -> 3
A98: POTUS VARIEGADO VERDE | B98: =+COMPRAS!B98:B176 -> COLGANTE | C98: =+InventarioTbl3[[#This Row],[Cantidad]] -> 7 | D98: =+InventarioTbl3[[#This Row],[Costo Unit.]] -> 3500 | E98: 8000 | F98: =+E98-InventarioTbl34[[#This Row],[Costo Unit.]] -> 4500 | G98: =C98-SUMIF(Ventas!D:D,"POTUS VARIEGADO VERDE",Ventas!F:F) -> 7
A99: =+InventarioTbl3[[#This Row],[ESPECIE]] -> PORTULACA (VERDOLAGA) | C99: =+InventarioTbl3[[#This Row],[Cantidad]] -> 60 | D99: =+InventarioTbl3[[#This Row],[Costo Unit.]] -> 700 | E99: 3000 | F99: =+E99-InventarioTbl34[[#This Row],[Costo Unit.]] -> 2300 | G99: =C99-SUMIF(Ventas!D:D,"VERDOLAGA",Ventas!F:F) -> 60
A100: RETAMA | C100: =+InventarioTbl3[[#This Row],[Cantidad]] -> 5 | D100: =+InventarioTbl3[[#This Row],[Costo Unit.]] -> 5000 | E100: 10000 | F100: =+E100-InventarioTbl34[[#This Row],[Costo Unit.]] -> 5000 | G100: =C100-SUMIF(Ventas!D:D,"RETAMA",Ventas!F:F) -> 5
...

Sheet macetas
A1: TIPO DE MACETA | B1: Cantidad | C1: Costo Unit. | D1: Precio Venta | E1: Margen Neto | F1: NETO TOTAL | G1: Existencias
A2: GOTAS | F2: =SUM(E4:E58) -> 733819.9
A3: GOTA MINI | B3: =1+6 -> 7 | C3: 4500 | D3: 10000 | E3: =+D3-C3 -> 5500 | G3: =B3-SUMIF(Ventas!D:D,"GOTA Nº20",Ventas!F:F) -> 7
A4: GOTA Nº25 | B4: 1 | C4: 7500 | D4: 15000 | E4: =+D4-C4 -> 7500 | G4: =B4-SUMIF(Ventas!D:D,"GOTA Nº25",Ventas!F:F) -> 0
A5: GOTA Nº30 | B5: 4 | C5: 8500 | D5: 20000 | E5: =+D5-C5 -> 11500 | G5: =B5-SUMIF(Ventas!D:D,"GOTA Nº30",Ventas!F:F) -> 0
A6: GOTA Nº35 | B6: 2 | C6: 15000 | D6: 30000 | E6: =+D6-C6 -> 15000 | G6: =B6-SUMIF(Ventas!D:D,"GOTA Nº35",Ventas!F:F) -> 2
A7: GOTA Nº40 | B7: =2+2+2 -> 6 | C7: 14000 | D7: 40000 | E7: =+D7-C7 -> 26000 | G7: =B7-SUMIF(Ventas!D:D,"GOTA Nº40",Ventas!F:F) -> 5
A8: GOTA Nº50 | B8: =1+2 -> 3 | C8: 18000 | D8: 50000 | E8: =+D8-C8 -> 32000 | G8: =B8-SUMIF(Ventas!D:D,"GOTA Nº50",Ventas!F:F) -> 0
A9: GOTA LARGA | B9: 4 | C9: 15000 | D9: 30000 | E9: =+D9-C9 -> 15000 | G9: =B9-SUMIF(Ventas!D:D,"GOTA LARGA",Ventas!F:F) -> 3
A10: GOTA Nº50 ANCHA | B10: 2 | C10: 22000 | D10: 55000 | E10: =+D10-C10 -> 33000 | G10: =B10-SUMIF(Ventas!D:D,"GOTA Nº50 ANCHA",Ventas!F:F) -> 1
A11: GOTA Nº65 ANCHA | B11: 2 | C11: 25000 | D11: 60000 | E11: =+D11-C11 -> 35000 | G11: =B11-SUMIF(Ventas!D:D,"GOTA Nº65 ANCHA",Ventas!F:F) -> 1
A12: GOTA Nº67 | B12: 1 | C12: 22000 | D12: 60000 | E12: =+D12-C12 -> 38000 | G12: =B12-SUMIF(Ventas!D:D,"GOTA Nº67",Ventas!F:F) -> 1
A13: TINAJA Nº 65 | B13: 1 | C13: 22000 | D13: 55000 | E13: =+D13-C13 -> 33000 | G13: =B13-SUMIF(Ventas!D:D,"TIJANA Nº65",Ventas!F:F) -> 1
A14: ESQUINEROS | B14: 4 | C14: 15500 | D14: 25000 | E14: =+D14-C14 -> 9500 | G14: =B14-SUMIF(Ventas!D:D,"ESQUINEROS",Ventas!F:F) -> 4
A15: CUBOS
A16: CUBO 40X40 | B16: 1 | C16: 15000 | D16: 40000 | E16: =+D16-C16 -> 25000 | G16: =B16-SUMIF(Ventas!D:D,"CUBO 40X40",Ventas!F:F) -> 1
A17: CUBO 35X35 | B17: 2 | C17: 11000 | D17: 30000 | E17: =+D17-C17 -> 19000 | G17: =B17-SUMIF(Ventas!D:D,"CUBO 35X35",Ventas!F:F) -> 2
A18: CUBO 25X25 | B18: 2 | C18: 6000 | D18: 15000 | E18: =+D18-C18 -> 9000 | G18: =B18-SUMIF(Ventas!D:D,"CUBO 25X25",Ventas!F:F) -> 1
A19: CUBO 15X15 | B19: =2+4 -> 6 | C19: 4000 | D19: 10000 | E19: =+D19-C19 -> 6000 | G19: =B19-SUMIF(Ventas!D:D,"CUBO 15X15",Ventas!F:F) -> 5
A20: CONOS
A21: CONO N40 | B21: 2 | C21: 10000 | D21: 30000 | E21: =+D21-C21 -> 20000 | G21: =B21-SUMIF(Ventas!D:D,"CONO N40",Ventas!F:F) -> 2
A22: CONO N55 | B22: 2 | C22: 15000 | D22: 40000 | E22: =+D22-C22 -> 25000 | G22: =B22-SUMIF(Ventas!D:D,"CONO N55",Ventas!F:F) -> 2
A23: CONO N70 | B23: 2 | C23: 18000 | D23: 50000 | E23: =+D23-C23 -> 32000 | G23: =B23-SUMIF(Ventas!D:D,"CONO N70",Ventas!F:F) -> 2
A24: PIRAMIDAL
A25: PIRAMIDAL 80X35 | B25: 1 | C25: 19000 | D25: 60000 | E25: =+D25-C25 -> 41000 | G25: =B25-SUMIF(Ventas!D:D,"PIRAMIDAL 80X35",Ventas!F:F) -> 1
A26: PIRAMIDAL 60X50 | B26: 1 | C26: 20000 | D26: 55000 | E26: =+D26-C26 -> 35000 | G26: =B26-SUMIF(Ventas!D:D,"PIRAMIDAL 60X50",Ventas!F:F) -> 1
A27: PIRAMIDAL 40X30 | B27: 5 | C27: 8000 | D27: 25000 | E27: =+D27-C27 -> 17000 | G27: =B27-SUMIF(Ventas!D:D,"PIRAMIDAL 40X30",Ventas!F:F) -> 1
A28: PIRAMIDAL 30X25 | B28: 2 | C28: 6000 | D28: 20000 | E28: =+D28-C28 -> 14000 | G28: =B28-SUMIF(Ventas!D:D,"PIRAMIDAL 30X25",Ventas!F:F) -> 2
A29: PIRAMIDAL 20X20 | B29: 2 | C29: 4000 | D29: 15000 | E29: =+D29-C29 -> 11000 | G29: =B29-SUMIF(Ventas!D:D,"PIRAMIDAL 20X20",Ventas!F:F) -> 2
A30: PIRAMIDAL 70X35 | B30: 2 | C30: 17000 | D30: 35000 | E30: =+D30-C30 -> 18000 | G30: =B30-SUMIF(Ventas!D:D,"PIRAMIDAL 70X35",Ventas!F:F) -> 2
A31: PRISMA
A32: PRISMA 60X20 | B32: 2 | C32: 9000 | D32: 30000 | E32: =+D32-C32 -> 21000 | G32: =B32-SUMIF(Ventas!D:D,"PRISMA 60X20",Ventas!F:F) -> 2
A33: PRISMA 50X20 | B33: 2 | C33: 8000 | D33: 25000 | E33: =+D33-C33 -> 17000 | G33: =B33-SUMIF(Ventas!D:D,"PRISMA 50X20",Ventas!F:F) -> 2
A34: PRISMA 40X20 | B34: =2+2 -> 4 | C34: 8500 | D34: 20000 | E34: =+D34-C34 -> 11500 | G34: =B34-SUMIF(Ventas!D:D,"PRISMA 40X20",Ventas!F:F) -> 4
A35: PRISMA 30X20 | B35: 2 | C35: 6000 | D35: 15000 | E35: =+D35-C35 -> 9000 | G35: =B35-SUMIF(Ventas!D:D,"PRISMA 30X20",Ventas!F:F) -> 1
A36: JARDINERAS
A37: JARDINERA 1X20X20 | B37: 2 | C37: 12000 | D37: 25000 | E37: =+D37-C37 -> 13000 | G37: =B37-SUMIF(Ventas!D:D,"JARDINERA 1X20X20",Ventas!F:F) -> 2
A38: JARDINERA 50X20X20 | B38: 1 | C38: 7000 | D38: 15000 | E38: =+D38-C38 -> 8000 | G38: =B38-SUMIF(Ventas!D:D,"JARDINERA 50X20X20",Ventas!F:F) -> -1
A39: JARDINERA 80X30X30 | B39: =1+2 -> 3 | C39: 14000 | D39: 30000 | E39: =+D39-C39 -> 16000 | G39: =B39-SUMIF(Ventas!D:D,"JARDINERA 80X30X30",Ventas!F:F) -> 3
A40: JARDINERA 1X22X40 | B40: 1 | C40: 19500 | D40: 50000 | E40: =+D40-C40 -> 30500 | G40: =B40-SUMIF(Ventas!D:D,"JARDINERA 1X22X40",Ventas!F:F) -> 1
A41: JARDINERA 60X22X30 | B41: 2 | C41: 11000 | D41: 25000 | E41: =+D41-C41 -> 14000 | G41: =B41-SUMIF(Ventas!D:D,"JARDINERA 60X22X30",Ventas!F:F) -> 2
A42: PLASTICAS
A43: JARDINERA ROCIO N35 | B43: 5 | C43: =1690.8+1000 -> 2690.8 | D43: 5500 | E43: =+D43-C43 -> 2809.2 | G43: =B43-SUMIF(Ventas!D:D,"JARDINERA ROCIO N35",Ventas!F:F) -> 5
A44: JARDINERA ROCIO N45 | B44: 4 | C44: =2368.44+1000 -> 3368.44 | D44: 6500 | E44: =+D44-C44 -> 3131.56 | G44: =B44-SUMIF(Ventas!D:D,"JARDINERA ROCIO N45",Ventas!F:F) -> 2
A45: JARDINERA ROCIO N55 | B45: 3 | C45: =3682.92+1000 -> 4682.92 | D45: 9000 | E45: =+D45-C45 -> 4317.08 | G45: =B45-SUMIF(Ventas!D:D,"JARDINERA ROCIO N55",Ventas!F:F) -> 3
A46: PREMIUM REDONDA N12 | B46: 2 | C46: =966.31+1000 -> 1966.31 | D46: 4000 | E46: =+D46-C46 -> 2033.69 | G46: =B46-SUMIF(Ventas!D:D,"PREMIUM REDONDA N12",Ventas!F:F) -> 2
A47: PREMIUM REDONDA N18 | B47: 5 | C47: =2040.51+1000 -> 3040.51 | D47: 6000 | E47: =+D47-C47 -> 2959.49 | G47: =B47-SUMIF(Ventas!D:D,"PREMIUM REDONDA N18",Ventas!F:F) -> 5
A48: PREMIUM REDONDA N08 | B48: 4 | C48: =506.61+1000 -> 1506.61 | D48: 3000 | E48: =+D48-C48 -> 1493.39 | G48: =B48-SUMIF(Ventas!D:D,"PIRAMIDAL OWEN N25",Ventas!F:F) -> 4
A49: PIRAMIDAL OWEN N25 | B49: 5 | C49: =4252.68+1000 -> 5252.68 | D49: 10500 | E49: =+D49-C49 -> 5247.32 | G49: =B49-SUMIF(Ventas!D:D,"PIRAMIDAL OWEN N25",Ventas!F:F) -> 5
A50: PIRAMIDAL OWEN N15 | B50: 6 | C50: =1828.38+1000 -> 2828.38 | D50: 5500 | E50: =+D50-C50 -> 2671.62 | G50: =B50-SUMIF(Ventas!D:D,"PIRAMIDAL OWEN N15",Ventas!F:F) -> 6
A51: PARIS N18 | B51: 6 | C51: =1716.84+1000 -> 2716.84 | D51: 6500 | E51: =+D51-C51 -> 3783.16 | G51: =B51-SUMIF(Ventas!D:D,"PARIS N18",Ventas!F:F) -> 0
A52: PARIS N27 | B52: 5 | C52: =5159.91+1000 -> 6159.91 | D52: 12000 | E52: =+D52-C52 -> 5840.09 | G52: =B52-SUMIF(Ventas!D:D,"PARIS N27",Ventas!F:F) -> 2
A53: DIAMANTE N25 | B53: 3 | C53: =3611.94+1000 -> 4611.94 | D53: 9500 | E53: =+D53-C53 -> 4888.06 | G53: =B53-SUMIF(Ventas!D:D,"DIAMANTE N25",Ventas!F:F) -> 2
A54: DIAMANTE N15 | B54: 4 | C54: =1107.04+1000 -> 2107.04 | D54: 4500 | E54: =+D54-C54 -> 2392.96 | G54: =B54-SUMIF(Ventas!D:D,"DIAMANTE N15",Ventas!F:F) -> 2
A55: MILAN N20 | B55: 8 | C55: =3002.13+1000 -> 4002.13 | D55: 8000 | E55: =+D55-C55 -> 3997.87 | G55: =B55-SUMIF(Ventas!D:D,"MILAN N20",Ventas!F:F) -> 4
A56: ROCIO N10 | B56: 10 | C56: =172.37+1000 -> 1172.37 | D56: 2000 | E56: =+D56-C56 -> 827.63 | G56: =B56-SUMIF(Ventas!D:D,"ROCIO N10",Ventas!F:F) -> 10
A57: VENECIA N17 | B57: 6 | C57: =2204.7+1000 -> 3204.7 | D57: 6500 | E57: =+D57-C57 -> 3295.3 | G57: =B57-SUMIF(Ventas!D:D,"VENECIA N17",Ventas!F:F) -> 3
A58: PIRAMIDAL N45 CON RUEDAS | B58: 5 | C58: =12368.52+1000 -> 13368.52 | D58: 30000 | E58: =+D58-C58 -> 16631.48 | G58: =B58-SUMIF(Ventas!D:D,"PIRAMIDAL N45 CON RUEDAS",Ventas!F:F) -> 3
A59: COLGANTE PLASTICA | B59: 3 | C59: 0 | D59: 8000 | E59: =+D59-C59 -> 8000 | G59: =B59-SUMIF(Ventas!D:D,"COLGANTE PLASTICA",Ventas!F:F) -> 0

Sheet Ventas
A1: Fecha | B1: Nombre Cliente | C1: Tel. | D1: Especie | E1: Maceta | F1: Cantidad | G1: Precio Unit. | H1: Total | I1: TOTAL JORNADA | J1: TOTAL PONDERADO
A2: 46243 | B2: DUEÑA DE CUBO | D2: CALATEA MIL RAYAS | E2: 3L | F2: 2 | G2: 18000 | H2: =F2*G2 -> 36000 | I2: =+H2+H3 -> 96000 | J2: =SUM(I2:I655) -> 8839400
A3: 46243 | B3: DUEÑA DE CUBO | D3: CALATEA MACOYANA | E3: 3L | F3: 3 | G3: 20000 | H3: =F3*G3 -> 60000
A4: 46247 | B4: CLIENTE | D4: TIERRA NEGRA | E4: 25L | F4: 1 | G4: 8000 | H4: =F4*G4 -> 8000 | I4: =+H4 -> 8000
A5: 46248 | B5: JUJEÑO RENE | D5: LIRIO DEL AMAZONAS | E5: 3L | F5: 1 | G5: 8000 | H5: =F5*G5 -> 8000 | I5: =+H5+H7+H8+H6 -> 28800
A6: 46248 | B6: CLIENTE | D6: VIOLETA | E6: 0.5 | F6: 1 | G6: 2000 | H6: =F6*G6 -> 2000
A7: 46248 | B7: CLIENTE | D7: JAZMIN AMARILLO | E7: 4L | F7: 1 | G7: 8800 | H7: =F7*G7 -> 8800
A8: 46248 | B8: CLIENTE | D8: HELECHO ESPARRAGO | E8: 4L | F8: 1 | G8: 10000 | H8: =F8*G8 -> 10000
A9: 46249 | B9: CLIENTE | D9: BEGONIA DRAGON | E9: 1L | F9: 1 | G9: 6000 | H9: =F9*G9 -> 6000 | I9: =+H9+H10+H11 -> 11000
A10: 46249 | B10: CLIENTE | D10: CEDRON PARAGUAYO | E10: 0,5 L | F10: 1 | G10: 2500 | H10: =F10*G10 -> 2500
A11: 46249 | B11: CLIENTE | D11: OREGANO | E11: 0,5 L | F11: 1 | G11: 2500 | H11: =F11*G11 -> 2500
A12: 46250 | B12: Clarisa lopez | D12: CURRY | E12: 0.5 | F12: 1 | G12: 3000 | H12: =F12*G12 -> 3000 | I12: =+H12+H13+H14+H15+H16 -> 28000
A13: 46250 | B13: Clarisa lopez | D13: DRACENA WARNECKI | E13: 1L | F13: 1 | G13: 12000 | H13: =F13*G13 -> 12000
A14: 46250 | B14: Clarisa lopez | D14: maceta PLASTICO gris | E14: 3L | F14: 1 | G14: 3000 | H14: =F14*G14 -> 3000
A15: 46250 | B15: mirta | D15: TIERRA NEGRA | E15: 20L | F15: 1 | G15: 8000 | H15: =F15*G15 -> 8000
A16: 46250 | B16: mirta | D16: mantillo | E16: 10L | F16: 1 | G16: 2000 | H16: =F16*G16 -> 2000
A17: 46251 | B17: Gringa | D17: CROTO PETRA | E17: 3L | F17: 1 | G17: 14000 | H17: =F17*G17 -> 14000 | I17: =+H17+H18+H19 -> 80500
A18: 46251 | B18: MIRTA CABRAL MOTORS | D18: OLIVO | E18: 10L | F18: 1 | G18: 60000 | H18: =F18*G18 -> 60000
A19: 46251 | B19: CLIENTE RISIONE | D19: DIETE | E19: 5L | F19: 1 | G19: 6500 | H19: =F19*G19 -> 6500
A20: 46255 | B20: CHICO OJOS CLAROS | D20: CROTON | E20: 5L | F20: 2 | G20: 16000 | H20: =F20*G20 -> 32000 | I20: =SUM(H20:H21) -> 48000
A21: 46255 | B21: CHICO OJOS CLAROS | D21: COLOCACIA ESCULENTA | F21: 2 | G21: 8000 | H21: =F21*G21 -> 16000
A22: 46256 | B22: CLIENTE | D22: GOMERO VARIEGADO | E22: 3 | F22: 1 | G22: 14000 | H22: =F22*G22 -> 14000 | I22: =SUM(H22:H43) -> 316500
A23: 46256 | B23: CLIENTE | D23: GOMERO COMUN 1L | E23: 1 | F23: 1 | G23: 11000 | H23: =F23*G23 -> 11000
A24: 46256 | B24: CLIENTE | D24: GOTA Nº30 | F24: 1 | G24: 20000 | H24: =F24*G24 -> 20000
A25: 46256 | B25: CLIENTE | D25: PALMITO | E25: 5 | F25: 1 | G25: 22000 | H25: =F25*G25 -> 22000
A26: 46256 | B26: CENTU | D26: COLOCACIA ESCULENTA | F26: 1 | G26: 8000 | H26: =F26*G26 -> 8000
A27: 46256 | B27: CENTU | D27: GOMERO PINK | F27: 1 | G27: 19000 | H27: =F27*G27 -> 19000
A28: 46256 | B28: CLIENTA | D28: LAVANDA | F28: 2 | G28: 10000 | H28: =F28*G28 -> 20000
A29: 46256 | D29: CURRY | F29: 2 | G29: 3000 | H29: =F29*G29 -> 6000
A30: 46256 | D30: TOMILLO | F30: 1 | G30: 3000 | H30: =F30*G30 -> 3000
A31: 46256 | D31: SALVIA | F31: 2 | G31: 9000 | H31: =F31*G31 -> 18000
A32: 46256 | D32: BOLSA TIERRA AZUL | F32: 1 | G32: 8000 | H32: =F32*G32 -> 8000
A33: 46256 | D33: MANTILLO | F33: 1 | G33: 3000 | H33: =F33*G33 -> 3000
A34: 46256 | D34: CROTON | F34: 1 | G34: 18000 | H34: =F34*G34 -> 18000
A35: 46256 | D35: JAZMIN AMARILLO | F35: 1 | G35: 9000 | H35: =F35*G35 -> 9000
A36: 46256 | D36: GOMERO VARIEGADO | F36: 1 | G36: 25000 | H36: =F36*G36 -> 25000
A37: 46256 | B37: NORMA | D37: DRACENA WARNECKI | F37: 1 | G37: 9000 | H37: =F37*G37 -> 9000
A38: 46256 | B38: NORMA | D38: DRACENA LEMON | F38: 1 | G38: 9000 | H38: =F38*G38 -> 9000
A39: 46256 | B39: NORMA | D39: GOTA MINI | F39: 2 | G39: 6000 | H39: =F39*G39 -> 12000
A40: 46256 | B40: CARLA VILLALVA | D40: ANTHURIUM | F40: 1 | G40: 12000 | H40: =F40*G40 -> 12000
A41: 46256 | B41: AMIGA CARLA | D41: ALISO DE MAR | F41: 2 | G41: 3500 | H41: =F41*G41 -> 7000
A42: 46256 | B42: CLIENTE | D42: GOTA Nº30 | F42: 2 | G42: 30000 | H42: =F42*G42 -> 60000
A43: 46256 | B43: CLIENTE | D43: CURRY | F43: 1 | G43: 3500 | H43: =F43*G43 -> 3500
A44: 46257 | B44: FAMILIA | D44: PENSAMIENTO | F44: 2 | G44: 2000 | H44: =F44*G44 -> 4000 | I44: =SUM(H44:H51) -> 69500
A45: 46257 | B45: FAMILIA | D45: BEGONIA DRAGON | F45: 1 | G45: 6000 | H45: =F45*G45 -> 6000
A46: 46257 | B46: CESAR | D46: COLEUS | F46: 1 | G46: 5000 | H46: =F46*G46 -> 5000
A47: 46257 | B47: CESAR | D47: CORONITA DE NOVIA | F47: 1 | G47: 20000 | H47: =F47*G47 -> 20000
A48: 46257 | B48: CESAR | D48: CURRY | F48: 1 | G48: 3000 | H48: =F48*G48 -> 3000
A49: 46257 | B49: CESAR | D49: CEDRON PARAGUAYO | F49: 1 | G49: 3000 | H49: =F49*G49 -> 3000
A50: 46257 | B50: CAMI HINDU | D50: DIETE | F50: 3 | G50: 6500 | H50: =F50*G50 -> 19500
A51: 46257 | B51: CLIENTA | D51: MACETA PLASTICO CELESTE | F51: 3 | G51: 3000 | H51: =F51*G51 -> 9000
A52: 46258 | B52: CLIENTES PANADERIA | D52: AREKA | F52: 1 | G52: 18000 | H52: =F52*G52 -> 18000 | I52: =SUM(H52:H57) -> 98000
A53: 46258 | B53: CLIENTES PANADERIA | D53: PIRAMIDAL 40X30 | F53: 1 | G53: 20000 | H53: =F53*G53 -> 20000
A54: 46258 | B54: CLIENTES PANADERIA | D54: DRACENA WARNECKI | F54: 1 | G54: 12000 | H54: =F54*G54 -> 12000
A55: 46258 | B55: CLIENTES PANADERIA | D55: CUBO 15X15 | F55: 1 | G55: 8000 | H55: =F55*G55 -> 8000
A56: 46258 | B56: JOSE | D56: CURRY | F56: 5 | G56: 3000 | H56: =F56*G56 -> 15000
A57: 46258 | B57: pablo alarcon | D57: GOMERO COMUN | F57: 1 | G57: 25000 | H57: =F57*G57 -> 25000
A58: 46259 | B58: JAVIER CLIENTE | D58: CUARESMERO | F58: 1 | G58: 22000 | H58: =F58*G58 -> 22000 | I58: =SUM(H58:H62) -> 56000
A59: 46259 | B59: JAVIER CLIENTE | D59: SEAFORTIA | F59: 1 | G59: 25000 | H59: =F59*G59 -> 25000
A60: 46259 | B60: EL NIÑO | D60: MACETA PLASTICO GRIS | F60: 1 | G60: 3000 | H60: =F60*G60 -> 3000
A61: 46259 | B61: EL NIÑO | D61: MANTILLO | F61: 1 | G61: 3000 | H61: =F61*G61 -> 3000
A62: 46259 | B62: JUJEÑA | D62: FROMERO | F62: 1 | G62: 3000 | H62: =F62*G62 -> 3000
A63: 46260 | B63: CLIENTA BARRIO | D63: COLEO | F63: 1 | G63: 5000 | H63: =F63*G63 -> 5000 | I63: =SUM(H63:H75) -> 260000
A64: 46260 | B64: CLIENTA SEÑA | D64: DORSTENIA | F64: 1 | G64: 20000 | H64: =F64*G64 -> 20000
A65: 46260 | B65: CLIENTA MARTA GIRAUDO | D65: FLORALES | F65: 5 | G65: 2000 | H65: =F65*G65 -> 10000
A66: 46260 | B66: vecina | D66: MANTILLO | F66: 1 | G66: 3000 | H66: =F66*G66 -> 3000
A67: 46260 | B67: PEGORARO SILVANA | D67: DRACENA LEMON | F67: 1 | G67: 9000 | H67: =F67*G67 -> 9000
A68: 46260 | B68: PEGORARO SILVANA | D68: DRACENA WARNECKI | F68: 1 | G68: 9000 | H68: =F68*G68 -> 9000
A69: 46260 | B69: NORMA BARRIENTOS | D69: ESCUDO PERSA | F69: 2 | G69: 3000 | H69: =F69*G69 -> 6000
A70: 46260 | B70: SEBASTIAN ALPERIN | D70: PALMITO | F70: 1 | G70: 22000 | H70: =F70*G70 -> 22000
A71: 46260 | B71: SEBASTIAN ALPERIN | D71: GOTA Nº30 | F71: 1 | G71: 20000 | H71: =F71*G71 -> 20000
A72: 46260 | B72: CHICA RUBIA | D72: GOTA Nº50 | F72: 1 | G72: 40000 | H72: =F72*G72 -> 40000
A73: 46260 | B73: PAREJA DE VIEJOS | D73: STRELITZIA REGINAE | F73: 1 | G73: 60000 | H73: =F73*G73 -> 60000
A74: 46260 | B74: PAREJA DE VIEJOS | D74: Nª41 CON RUEDAS | F74: 1 | G74: 40000 | H74: =F74*G74 -> 40000
A75: 46260 | B75: VECINA BARRIO | D75: CROTO LENGUA DE FUEGO | F75: 1 | G75: 16000 | H75: =F75*G75 -> 16000
A76: 46261 | B76: MONICA FRANCO | D76: BEGONIA ALAS DE ANGEL | F76: 1 | G76: 10000 | H76: =F76*G76 -> 10000 | I76: =SUM(H76:H81) -> 79000
A77: 46261 | B77: MONICA FRANCO | D77: MARANTA ORACION | F77: 1 | G77: 5000 | H77: =F77*G77 -> 5000
A78: 46261 | B78: ELSA CHETA | D78: LAVANDA | F78: 3 | G78: 8000 | H78: =F78*G78 -> 24000
A79: 46261 | B79: ELSA CHETA | D79: SALVIA | F79: 2 | G79: 8500 | H79: =F79*G79 -> 17000
A80: 46261 | B80: PAREJA DE BS AS | D80: DRACENA RUBRA | F80: 1 | G80: 8000 | H80: =F80*G80 -> 8000
A81: 46261 | B81: PAREJA DE BS AS | D81: AGUARIBAY | F81: 1 | G81: 15000 | H81: =F81*G81 -> 15000
A82: 46262 | B82: viejita | D82: MARANTA ORACION | F82: 1 | G82: 4500 | H82: =F82*G82 -> 4500 | I82: =SUM(H82:H101) -> 374500
A83: 46262 | B83: pareja de viejos | D83: AZALEA | F83: 1 | G83: 10000 | H83: =F83*G83 -> 10000
A84: 46262 | B84: almiron maria ines | D84: GAURA | F84: 2 | G84: 8500 | H84: =F84*G84 -> 17000
A85: 46262 | B85: almiron maria ines | D85: SALVIA | F85: 1 | G85: 9000 | H85: =F85*G85 -> 9000
A86: 46262 | B86: almiron maria ines | D86: TIERRA NEGRA BOLSA AZUL | F86: 2 | G86: 8000 | H86: =F86*G86 -> 16000
A87: 46262 | B87: vecina mantera | D87: PHILODENDRO WHITE PRINCESS | F87: 1 | G87: 25000 | H87: =F87*G87 -> 25000
A88: 46262 | B88: vecina mantera | D88: ROMERO PEQUEÑO | F88: 1 | G88: 3000 | H88: =F88*G88 -> 3000
A89: 46262 | B89: vecina mantera | D89: BEGONIA DRAGON | F89: 1 | G89: 6000 | H89: =F89*G89 -> 6000
A90: 46262 | B90: vecina mantera | D90: TIERRA NEGRA BOLSA AZUL | F90: 1 | G90: 8000 | H90: =F90*G90 -> 8000
A91: 46262 | B91: vecina mantera | D91: TREBOL ROJO | F91: 1 | G91: 9000 | H91: =F91*G91 -> 9000
A92: 46262 | B92: SEBASTIAN UNNE | D92: MONSTERA | F92: 1 | G92: 12000 | H92: =F92*G92 -> 12000
A93: 46262 | B93: LILIANA FALCON | D93: FLORALES | F93: 5 | G93: 2000 | H93: =F93*G93 -> 10000
A94: 46262 | B94: LILIANA FALCON | D94: ALISO DE MAR | F94: 3 | G94: 3000 | H94: =F94*G94 -> 9000
... A101: 46262 | B101: CLIENTA | D101: JARDINERA 50X20X20 | F101: 2 | G101: 18000 | H101: =F101*G101 -> 36000
A102: 46263 | B102: MANUEL SOLA | D102: FLORALES | F102: 3 | G102: 2000 | H102: =F102*G102 -> 6000 | I102: =SUM(H102:H128) -> 369300
A103: 46263 | B103: MANUEL SOLA | D103: ALISO DE MAR | F103: 1 | G103: 3000 | H103: =F103*G103 -> 3000
A104: 46263 | B104: PROFE UNNE | D104: CORONITA DE NOVIA | F104: 1 | G104: 18000 | H104: =F104*G104 -> 18000
A105: 46263 | B105: PROFE UNNE | D105: ANTHURIUM | F105: 1 | G105: 12000 | H105: =F105*G105 -> 12000
A106: 46263 | B106: PROFE UNNE | D106: ESPATIFILO | F106: 1 | G106: 18000 | H106: =F106*G106 -> 18000
...

Sheet Costos
A1: COSTOS FIJOS | B1: 2026
A2: Concepto | B2: ABRIL | C2: MAYO | D2: JUNIO | E2: JULIO | F2: AGOSTO | G2: SEPTIEMBRE | H2: OCTUBRE | I2: NOVIEMBRE | J2: DICIEMBRE
A3: LUZ | B3: 42486.29 | C3: 42486.29 | D3: 42486.29 | E3: 42486.29 | F3: 42486.29 | G3: 42486.29 | H3: 42486.29 | I3: 42486.29 | J3: 42486.29
A4: AGUA | B4: 33498.05 | C4: 33498.05 | D4: 33498.05 | E4: 33498.05 | F4: 33498.05 | G4: 33498.05 | H4: 33498.05 | I4: 33498.05 | J4: 33498.05
A5: INTERNET | B5: 25000 | C5: 25000 | D5: 25000 | E5: 25000 | F5: 25000 | G5: 25000 | H5: 25000 | I5: 25000 | J5: 25000
A6: CAMARA | B6: 20000 | C6: 20000 | D6: 20000 | E6: 20000 | F6: 20000 | G6: 20000 | H6: 20000 | I6: 20000 | J6: 20000
A7: JORNALES
A9: COSTOS VARIABLES | B9: 2026
A10: concepto | B10: ABRIL | C10: MAYO | D10: JUNIO | E10: JULIO | F10: AGOSTO | G10: SEPTIEMBRE | H10: OCTUBRE | I10: NOVIEMBRE | J10: DICIEMBRE
A11: TIERRA NEGRA
A12: PLANTAS
A13: MACETAS
A14: SUSTRATOS
A15: FERTILIZANTES
A16: FITOSANITARIOS
A17: PIEDRAS
A18: COMBUSTIBLE

Sheet FlujoCaja
A1: Fecha | B1: Ingresos | C1: Egresos | D1: Saldo
A2: 46243 | B2: =SUM(Ventas!H2:H3) -> 96000 | D2: =B2-C2 -> 96000
A3: 46247 | B3: 8000 | D3: =B3-C3 -> 8000
A4: 46248 | B4: 28800 | D4: =B4-C4 -> 28800
A5: 46249 | B5: 11000 | D5: =B5-C5 -> 11000
A6: 46250 | B6: 28000 | D6: =B6-C6 -> 28000
A7: 46251 | B7: 80500 | D7: 80500
D10: =SUM(D2:D7) -> 252300
